ourcustompkg/__init__.py
ourcustompkg/yolov7/__init__.py
ourcustompkg/yolov7/datasets.py
ourcustompkg/yolov7/detect.py
ourcustompkg/yolov7/detect_car.py
ourcustompkg/yolov7/export.py
ourcustompkg/yolov7/hubconf.py
ourcustompkg/yolov7/test.py
ourcustompkg/yolov7/train.py
ourcustompkg/yolov7/train_aux.py
ourcustompkg/yolov7/cfg/__init__.py
ourcustompkg/yolov7/data/__init__.py
ourcustompkg/yolov7/deploy/__init__.py
ourcustompkg/yolov7/figure/__init__.py
ourcustompkg/yolov7/inference/__init__.py
ourcustompkg/yolov7/models/__init__.py
ourcustompkg/yolov7/models/common.py
ourcustompkg/yolov7/models/experimental.py
ourcustompkg/yolov7/models/yolo.py
ourcustompkg/yolov7/scripts/__init__.py
ourcustompkg/yolov7/tools/__init__.py
ourcustompkg/yolov7/utils/__init__.py
ourcustompkg/yolov7/utils/activations.py
ourcustompkg/yolov7/utils/add_nms.py
ourcustompkg/yolov7/utils/autoanchor.py
ourcustompkg/yolov7/utils/datasets.py
ourcustompkg/yolov7/utils/general.py
ourcustompkg/yolov7/utils/google_utils.py
ourcustompkg/yolov7/utils/loss.py
ourcustompkg/yolov7/utils/metrics.py
ourcustompkg/yolov7/utils/plots.py
ourcustompkg/yolov7/utils/torch_utils.py
ourcustompkg/yolov7/utils/aws/__init__.py
ourcustompkg/yolov7/utils/aws/resume.py
ourcustompkg/yolov7/utils/wandb_logging/__init__.py
ourcustompkg/yolov7/utils/wandb_logging/log_dataset.py
ourcustompkg/yolov7/utils/wandb_logging/wandb_utils.py
ourcustompkg-0.14.dist-info/METADATA
ourcustompkg-0.14.dist-info/WHEEL
ourcustompkg-0.14.dist-info/entry_points.txt
ourcustompkg-0.14.dist-info/top_level.txt
ourcustompkg-0.14.dist-info/RECORD
