Metadata-Version: 2.1
Name: ourcustompkg
Version: 0.14
Summary: A robust YOLOv7-based package designed for efficient toy car detection and comprehensive dataset management.
Home-page: https://github.com/NeuroLeapTeam/gesture_recognition.git
Author: Brandon & Moshiur
Author-email: brandon@neuroleapmail.com, moshiur@neuroleapmail.com
Project-URL: Bug Tracker, https://github.com/NeuroLeapTeam/gesture_recognition/issues
Project-URL: Documentation, https://github.com/NeuroLeapTeam/gesture_recognition/wiki
Project-URL: Source Code, https://github.com/NeuroLeapTeam/gesture_recognition
Keywords: YOLOv7,toy car detection,dataset management,computer vision,deep learning
Classifier: Development Status :: 4 - Beta
Classifier: Programming Language :: Python :: 3
Classifier: Programming Language :: Python :: 3.6
Classifier: Programming Language :: Python :: 3.7
Classifier: Programming Language :: Python :: 3.8
Classifier: Programming Language :: Python :: 3.9
Classifier: License :: OSI Approved :: MIT License
Classifier: Operating System :: OS Independent
Classifier: Topic :: Scientific/Engineering :: Artificial Intelligence
Classifier: Topic :: Software Development :: Libraries :: Python Modules
Classifier: Intended Audience :: Developers
Classifier: Intended Audience :: Science/Research
Requires-Python: >=3.6
Requires-Dist: torch>=1.7.0
Requires-Dist: torchvision>=0.8.0
Requires-Dist: opencv-python>=4.1.2
Requires-Dist: numpy>=1.18.5
Requires-Dist: Pillow>=7.2.0
Requires-Dist: tqdm>=4.41.0
Requires-Dist: mediapipe>=0.8.9
Requires-Dist: tensorflow>=2.4.0
Requires-Dist: matplotlib>=3.2.2
Requires-Dist: scipy>=1.4.1
Requires-Dist: pyyaml>=5.3.1
Requires-Dist: seaborn>=0.11.0
Requires-Dist: pandas>=1.1.5
Requires-Dist: scikit-learn>=0.24.1
Requires-Dist: requests>=2.23.0
